odoo/addons/sale_order_tag/README.rst
odoo/addons/sale_order_tag/__init__.py
odoo/addons/sale_order_tag/__manifest__.py
odoo/addons/sale_order_tag/data/sale_order_tag_data.xml
odoo/addons/sale_order_tag/i18n/ca.po
odoo/addons/sale_order_tag/i18n/es.po
odoo/addons/sale_order_tag/i18n/it.po
odoo/addons/sale_order_tag/i18n/sale_order_tag.pot
odoo/addons/sale_order_tag/i18n/tr.po
odoo/addons/sale_order_tag/models/__init__.py
odoo/addons/sale_order_tag/models/sale_order.py
odoo/addons/sale_order_tag/models/sale_order_tag.py
odoo/addons/sale_order_tag/readme/CONTRIBUTORS.rst
odoo/addons/sale_order_tag/readme/DESCRIPTION.rst
odoo/addons/sale_order_tag/readme/USAGE.rst
odoo/addons/sale_order_tag/security/ir.model.access.csv
odoo/addons/sale_order_tag/security/sale_order_tag_security.xml
odoo/addons/sale_order_tag/static/description/icon.png
odoo/addons/sale_order_tag/static/description/index.html
odoo/addons/sale_order_tag/views/sale_order.xml
odoo/addons/sale_order_tag/views/sale_order_tag.xml
odoo14_addon_sale_order_tag-14.0.1.0.3.dev1.dist-info/METADATA
odoo14_addon_sale_order_tag-14.0.1.0.3.dev1.dist-info/WHEEL
odoo14_addon_sale_order_tag-14.0.1.0.3.dev1.dist-info/top_level.txt
odoo14_addon_sale_order_tag-14.0.1.0.3.dev1.dist-info/RECORD
